duke_standard_add_on_template/__init__.py
duke_standard_add_on_template/addon_prefs.py
duke_standard_add_on_template/app_handlers.py
duke_standard_add_on_template/bprops.py
duke_standard_add_on_template/duke/__init__.py
duke_standard_add_on_template/duke/_generated/__init__.py
duke_standard_add_on_template/duke/_internal/__init__.py
duke_standard_add_on_template/gui.py
duke_standard_add_on_template/ops.py
duke_standard_add_on_template-0.1.0.dist-info/METADATA
duke_standard_add_on_template-0.1.0.dist-info/WHEEL
duke_standard_add_on_template-0.1.0.dist-info/RECORD
