Metadata-Version: 2.3
Name: duke-standard-add-on-template
Version: 0.1.0
Summary: 
Author: clutch-or-kick
Author-email: spoklonskyi@gmail.com
Requires-Python: >=3.9
Classifier: Programming Language :: Python :: 3
Classifier: Programming Language :: Python :: 3.9
Classifier: Programming Language :: Python :: 3.10
Classifier: Programming Language :: Python :: 3.11
Classifier: Programming Language :: Python :: 3.12
Classifier: Programming Language :: Python :: 3.13
Requires-Dist: fake-bpy-module-4-2 (>=20250130,<20250131)
